{
  "id": "text_image_right",
  "type": "SharedSlice",
  "name": "TextImageRight",
  "description": "TextImageRight",
  "variations": [
    {
      "id": "default-slice",
      "name": "Default slice",
      "docURL": "...",
      "version": "sktwi1xtmkfgx8626",
      "description": "TextImageRight",
      "primary": {
        "textField": {
          "type": "StructuredText",
          "config": {
            "label": "Title",
            "placeholder": "Enter Title",
            "allowTargetBlank": true,
            "single": "heading1"
          }
        },
        "image": {
          "config": {
            "label": "image",
            "constraint": {},
            "thumbnails": []
          },
          "type": "Image"
        }
      },
      "items": {
        "richtext": {
          "config": {
            "label": "richtext",
            "placeholder": "Enter Description",
            "allowTargetBlank": true,
            "multi": "heading1,heading2,heading3,paragraph"
          },
          "type": "StructuredText"
        }
      }
    },
    {
      "id": "textImageLeft",
      "name": "TextImageLeft",
      "docURL": "...",
      "version": "sktwi1xtmkfgx8626",
      "description": "TextImageRight",
      "primary": {
        "textField": {
          "type": "StructuredText",
          "config": {
            "label": "Title",
            "placeholder": "Enter Title",
            "allowTargetBlank": true,
            "single": "heading1"
          }
        },
        "image": {
          "config": {
            "label": "image",
            "constraint": {},
            "thumbnails": []
          },
          "type": "Image"
        }
      },
      "items": {}
    },
    {
      "id": "titleImage",
      "name": "TitleImage",
      "docURL": "...",
      "version": "sktwi1xtmkfgx8626",
      "description": "TextImageRight",
      "primary": {
        "title": {
          "config": {
            "label": "title",
            "placeholder": "Enter Title",
            "allowTargetBlank": true,
            "single": "paragraph,preformatted,heading1,heading2,heading3,heading4,heading5,heading6,strong,em,hyperlink,image,embed,list-item,o-list-item,rtl"
          },
          "type": "StructuredText"
        },
        "image": {
          "config": {
            "label": "image",
            "constraint": {},
            "thumbnails": []
          },
          "type": "Image"
        }
      },
      "items": {}
    }
  ]
}